todoist_to_sqlite/__init__.py
todoist_to_sqlite/cli.py
todoist_to_sqlite/utils.py
todoist_to_sqlite-0.2.dist-info/LICENSE
todoist_to_sqlite-0.2.dist-info/METADATA
todoist_to_sqlite-0.2.dist-info/WHEEL
todoist_to_sqlite-0.2.dist-info/entry_points.txt
todoist_to_sqlite-0.2.dist-info/top_level.txt
todoist_to_sqlite-0.2.dist-info/RECORD
