Metadata-Version: 2.1
Name: todoist-to-sqlite
Version: 0.2
Summary: Save data from Todoist to a SQLite database
Home-page: https://github.com/bcongdon/todoist-to-sqlite
Author: Benjamin Congdon
Author-email: me@bcon.gdn
License: UNKNOWN
Project-URL: Source, https://github.com/bcongdon/todoist-to-sqlite
Project-URL: Issues, https://github.com/bcongdon/todoist-to-sqlite/issues
Keywords: todoist sqlite export dogsheep
Platform: UNKNOWN
Classifier: Development Status :: 5 - Production/Stable
Classifier: Environment :: Console
Classifier: Programming Language :: Python :: 3
Classifier: Programming Language :: Python :: 3.6
Classifier: Programming Language :: Python :: 3.7
Classifier: Programming Language :: Python :: 3.8
Classifier: Topic :: Database
Requires-Dist: click
Requires-Dist: requests
Requires-Dist: sqlite-utils (~=3.1)
Requires-Dist: tqdm (~=4.36)
Requires-Dist: pytodoist (~=2.1)
Provides-Extra: test
Requires-Dist: pytest ; extra == 'test'
